{
  "collectionName": "components_shared_contact_infos",
  "info": {
    "displayName": "Contact Info"
  },
  "options": {},
  "attributes": {
    "title": {
      "type": "string"
    },
    "description": {
      "type": "blocks"
    },
    "background": {
      "type": "component",
      "repeatable": false,
      "component": "attributes.background"
    },
    "padding": {
      "type": "component",
      "repeatable": false,
      "component": "attributes.padding"
    },
    "margin": {
      "type": "component",
      "repeatable": false,
      "component": "attributes.margin"
    },
    "position": {
      "type": "component",
      "repeatable": false,
      "component": "attributes.position"
    }
  }
}
